pytest_exploratory/__init__.py
pytest_exploratory/interactive.py
pytest_exploratory/ipython.py
pytest_exploratory/py.typed
pytest_exploratory-0.9.1.dist-info/LICENSE
pytest_exploratory-0.9.1.dist-info/METADATA
pytest_exploratory-0.9.1.dist-info/WHEEL
pytest_exploratory-0.9.1.dist-info/top_level.txt
pytest_exploratory-0.9.1.dist-info/RECORD
